hyssop_aiodb/__init__.py
hyssop_aiodb/component/__init__.py
hyssop_aiodb/component/aiodb_mixin.py
hyssop_aiodb/component/aiodb/__init__.py
hyssop_aiodb/component/aiodb/component.py
hyssop_aiodb/component/aiodb/constants.py
hyssop_aiodb/component/aiodb/local.csv
hyssop_aiodb/component/aiodb/utils.py
hyssop_aiodb/unit_test/__init__.py
hyssop_aiodb/unit_test/ut.py
hyssop_aiodb-0.0.9.dist-info/LICENSE
hyssop_aiodb-0.0.9.dist-info/METADATA
hyssop_aiodb-0.0.9.dist-info/WHEEL
hyssop_aiodb-0.0.9.dist-info/top_level.txt
hyssop_aiodb-0.0.9.dist-info/RECORD
