Metadata-Version: 2.1
Name: hyssop-aiodb
Version: 0.0.9
Summary: Extended hyssop components and utilities
Home-page: https://github.com/hsky77/hyssop
Author: hsky77
Author-email: howardlkung@gmail.com
License: MIT License
Platform: UNKNOWN
Classifier: Programming Language :: Python :: 3
Classifier: Programming Language :: Python :: 3.6
Classifier: Programming Language :: Python :: 3.7
Classifier: Programming Language :: Python :: 3.8
Classifier: License :: OSI Approved :: MIT License
Classifier: Operating System :: OS Independent
Requires-Python: >=3.6
License-File: LICENSE
Requires-Dist: hyssop >=1.1.7
Requires-Dist: sqlalchemy ==1.3.20
Requires-Dist: aiomysql ==0.2.0
Requires-Dist: aiosqlite ==0.20.0
